[
          {
                    "featureType": "background",
                    "elementType": "all",
                    "stylers": {
                              "color": "#212121"
                    }
          },
		  {
                    "featureType": "water",
                    "elementType": "geometry",
                    "stylers": {
                              "color": "#181818"
                    }
          },
          {
                    "featureType": "highway",
                    "elementType": "geometry.fill",
                    "stylers": {
                              "color": "#646255"
                    }
          },
          {
                    "featureType": "highway",
                    "elementType": "geometry.stroke",
                    "stylers": {
                              "color": "#49463d"
                    }
          },
          {
                    "featureType": "localRoad",
                    "elementType": "geometry.fill",
                    "stylers": {
                              "color": "#3a3a3a"
                    }
          },
          {
                    "featureType": "localRoad",
                    "elementType": "geometry.stroke",
                    "stylers": {
                              "color": "#262626"
                    }
          },
          {
                    "featureType": "land",
                    "elementType": "all",
                    "stylers": {
                              "color": "#1b1b1b"
                    }
          },
          {
                    "featureType": "green",
                    "elementType": "all",
                    "stylers": {
                              "color": "#1b1b1b"
                    }
          },
          {
                    "featureType": "railway",
                    "elementType": "geometry.fill",
                    "stylers": {
                              "color": "#5c5c5c"
                    }
          },
          {
                    "featureType": "railway",
                    "elementType": "geometry.stroke",
                    "stylers": {
                              "color": "#949494"
                    }
          },
          {
                    "featureType": "subway",
                    "elementType": "geometry.fill",
                    "stylers": {
                              "color": "#46181a"
                    }
          },
          {
                    "featureType": "subway",
                    "elementType": "geometry.stroke",
                    "stylers": {
                              "color": "#1b0f0f"
                    }
          },
          {
                    "featureType": "poi",
                    "elementType": "labels.text.fill",
                    "stylers": {
                              "color": "#8b8787"
                    }
          },
          {
                    "featureType": "poi",
                    "elementType": "labels.text.stroke",
                    "stylers": {
                              "color": "#313131"
                    }
          },
          {
                    "featureType": "roadLabel",
                    "elementType": "labels.text.fill",
                    "stylers": {
                              "color": "#8b8787"
                    }
          },
          {
                    "featureType": "roadLabel",
                    "elementType": "labels.text.stroke",
                    "stylers": {
                              "color": "#313131"
                    }
          }
]